pdfmerger/__init__.py
pdfmerger-0.5.0.dist-info/LICENSE
pdfmerger-0.5.0.dist-info/METADATA
pdfmerger-0.5.0.dist-info/WHEEL
pdfmerger-0.5.0.dist-info/top_level.txt
pdfmerger-0.5.0.dist-info/RECORD
